SPARQL_parser/SPARQL_parser.py
SPARQL_parser/__init__.py
SPARQL_parser-0.0.2.dist-info/LICENSE
SPARQL_parser-0.0.2.dist-info/METADATA
SPARQL_parser-0.0.2.dist-info/WHEEL
SPARQL_parser-0.0.2.dist-info/top_level.txt
SPARQL_parser-0.0.2.dist-info/RECORD
