Metadata-Version: 2.1
Name: SPARQL-parser
Version: 0.0.2
Summary: This is a SPARQL-parser, help you to get component of a SPARQL easily
Home-page: https://github.com/cdhx/SPARQL-parse
Author: njucsxh
Author-email: csxianghuang@gmail.com
License: UNKNOWN
Platform: UNKNOWN
Classifier: Programming Language :: Python :: 3
Classifier: License :: OSI Approved :: MIT License
Classifier: Operating System :: OS Independent
